<?xml version="1.0" encoding="UTF-8"?><record_update table="catalog_ui_policy_action">
    <catalog_ui_policy_action action="INSERT_OR_UPDATE">
        <catalog_item display_value="New Source of Wealth">98aac212fb622e108cb7f0f56eefdc8d</catalog_item>
        <catalog_variable>IO:2212de1efb622e108cb7f0f56eefdcf9</catalog_variable>
        <cleared>false</cleared>
        <disabled>ignore</disabled>
        <field/>
        <field_message/>
        <field_message_type>none</field_message_type>
        <mandatory>ignore</mandatory>
        <order>100</order>
        <sys_class_name>catalog_ui_policy_action</sys_class_name>
        <sys_created_by>admin</sys_created_by>
        <sys_created_on>2025-07-07 16:00:02</sys_created_on>
        <sys_id>797fe6dafb262e108cb7f0f56eefdc80</sys_id>
        <sys_mod_count>0</sys_mod_count>
        <sys_name>unemployed_or_retired_income_source</sys_name>
        <sys_package display_value="AI Agents - IMA In-Good-Order" source="x_snc_ai_agents_0">7084b0dc2b5a2a50c246fb466e91bfba</sys_package>
        <sys_policy/>
        <sys_scope display_value="AI Agents - IMA In-Good-Order">7084b0dc2b5a2a50c246fb466e91bfba</sys_scope>
        <sys_update_name>catalog_ui_policy_action_797fe6dafb262e108cb7f0f56eefdc80</sys_update_name>
        <sys_updated_by>admin</sys_updated_by>
        <sys_updated_on>2025-07-07 16:00:02</sys_updated_on>
        <table/>
        <ui_policy display_value="Show Retired / Unemployed Source of Income">98de6e5afb262e108cb7f0f56eefdcd3</ui_policy>
        <value/>
        <value_action>ignore</value_action>
        <variable>unemployed_or_retired_income_source</variable>
        <variable_set/>
        <visible>true</visible>
    </catalog_ui_policy_action>
    <sys_translated_text action="delete_multiple" query="documentkey=797fe6dafb262e108cb7f0f56eefdc80"/>
</record_update>
